FalconVision.py
clear.py
falconvision-0.0.2.dist-info/licenses/LICENSE
falconvision-0.0.2.dist-info/METADATA
falconvision-0.0.2.dist-info/WHEEL
falconvision-0.0.2.dist-info/top_level.txt
falconvision-0.0.2.dist-info/RECORD
