Metadata-Version: 2.4
Name: FalconVision
Version: 0.0.2
Summary: FalconVision gives insight on Minecraft servers!
Author: Invizabel
Project-URL: Homepage, https://github.com/Invizabel/FalconVision
Project-URL: Bug Tracker, https://github.com/Invizabel/FalconVision/issues
Classifier: Programming Language :: Python :: 3
Classifier: License :: OSI Approved :: MIT License
Classifier: Operating System :: OS Independent
Requires-Python: >=3.8
License-File: LICENSE
Dynamic: license-file
